datalineage/__init__.py
datalineage/cli.py
datalineage/lineage.py
datalineage/logger.py
datalineage/model.py
datalineage/util.py
datalineage/node/__init__.py
datalineage/node/column_node.py
datalineage/node/cte_node.py
datalineage/node/node.py
datalineage/node/node_visitor.py
datalineage/node/select_node.py
datalineage/node/subquery_node.py
datalineage/node/table_node.py
datalineage/node/union_node.py
datalineage/node/unknown_node.py
datalineage/renderer/__init__.py
datalineage/renderer/json_renderer.py
datalineage/renderer/mermaid_renderer.py
datalineage/renderer/renderer.py
datalineage/schema_retriever/schema_retriever.py
datalineage/schema_retriever/sqlalchemy_schema_retriever.py
datalineage/schema_retriever/static_schema_retriever.py
datalineage/serializer/serializer.py
datalineage/visitor/pretty_name_visitor.py
sql_datalineage-0.0.15.dist-info/METADATA
sql_datalineage-0.0.15.dist-info/WHEEL
sql_datalineage-0.0.15.dist-info/entry_points.txt
sql_datalineage-0.0.15.dist-info/licenses/LICENSE
sql_datalineage-0.0.15.dist-info/RECORD
