Metadata-Version: 2.4
Name: sql-datalineage
Version: 0.0.15
Summary: A project to build and visualize data lineage from SQL written in python. It supports column level lineage and can combine with metadata retriever for better result.
Project-URL: Homepage, https://github.com/viplazylmht/sql-datalineage
Project-URL: Source, https://github.com/viplazylmht/sql-datalineage
Project-URL: Issues, https://github.com/viplazylmht/sql-datalineage/issues
Author-email: Duy Ha <viplazylmt@gmail.com>
License: MIT
License-File: LICENSE
Keywords: column-level-lineage,data,lineage
Classifier: Development Status :: 3 - Alpha
Classifier: Intended Audience :: Developers
Classifier: Intended Audience :: Science/Research
Classifier: License :: OSI Approved :: MIT License
Classifier: Operating System :: OS Independent
Classifier: Programming Language :: Python :: 3 :: Only
Classifier: Programming Language :: SQL
Requires-Python: >=3.8
Requires-Dist: click
Requires-Dist: ipython>=8.12.3
Requires-Dist: jinja2>=3.1.5
Requires-Dist: pydantic==2.*
Requires-Dist: pyyaml>=6.0.2
Requires-Dist: requests
Requires-Dist: sqlalchemy>=2.0.36
Requires-Dist: sqlglot[rs]
